door_lock.v
module door_lock(input clk,input reset,input [3:0]password_entry,input enter,output unlock,output ALARM);

parameter s0=4'd0,s1=4'd1,s2=4'd2,s3=4'd3;
parameter attempts=4'd3;
parameter hold=4'd10;
parameter alarm_time=4'd10;
parameter password=4'b1100;

reg [3:0]state,next_state;
reg [3:0]count,timer,alaarm;
wire correct;

reg enter_d;
always @(posedge clk) enter_d <= enter;
wire enter_pulse = enter & ~enter_d;

assign correct = (password_entry==password);

always @(posedge clk)begin
    if(reset)
    state<=s0;
    else
    state<=next_state;
end

always @(posedge clk) begin
if(reset)
count<=4'd0;
else if(state==s2 && count!=attempts)
count<=count+1;
else if(state==s1)
count<=0;
else if(state==s3 && alaarm==alarm_time)
count<=0;
end

always @(posedge clk) begin
    if(reset)
    timer<=0;
    else if(state==s1 && timer!=hold)
    timer<=timer+1;
    else
    timer<=0;
end

always @(posedge clk) begin
    if(reset)
    alaarm<=0;
    else if(state==s3 && alaarm!=alarm_time)
    alaarm<=alaarm+1;
    else
    alaarm<=0;
end


always @(*) begin
    next_state=state;
    case(state) 
   s0:begin
    if(correct && enter_pulse)
    next_state=s1;
    else if(enter_pulse && !correct)
    next_state=s2;
   end

    s2:begin
        if(count==attempts-1)
        next_state=s3;
        else
        next_state=s0;
    end

    s1:begin
        if(timer!=hold)
        next_state=s1;
        else 
        next_state=s0;
    end

    s3: begin
        if(alaarm!=alarm_time)
        next_state=s3;
        else
        next_state=s0;
    end

    default:
        next_state=s0;
endcase
end

assign unlock=(state==s1);
assign ALARM=(state==s3);
endmodule

door_lock_tb.v
module door_lock_tb;

door_lock dut(.clk(clk),.reset(reset),.password_entry(password_entry),.enter(enter),.unlock(unlock),.ALARM(ALARM));

reg [3:0]password_entry;
reg enter,clk,reset;
 wire ALARM,unlock;

 initial begin
    clk=0;
    forever begin
    #5 clk=~clk;
    end
 end

 initial begin
    reset=1;
    #12 reset=0;
 end

 initial begin
enter=0;
password_entry=0;
    #10
    password_entry=4'b0101;
    enter=1;
    #10
    enter=0;
    #10
    password_entry=4'b1100;
    enter=1;
    #10 enter=1;
    #10 enter=0;
    #10 
    password_entry=4'b1001;
    enter=1;
    #10 enter=0;
    #10 
    password_entry=4'b1000;
    enter=1;
    #10 enter=0;
    #70 
    password_entry=4'b1101;
    enter=1;
    #10 enter=0;

    #200 $finish;
    end

initial begin
    $dumpfile("dump.vcd");
    $dumpvars(0,door_lock_tb);
    $monitor("Time=%0t,reset=%b,password_entry=%b,enter=%b,ALARM=%b,unlock=%b,count=%d,timer=%d,alaarm=%d",$time,reset,password_entry,enter,ALARM,unlock,dut.count,dut.timer,dut.alaarm);
 end
 endmodule

dump.vcd
$date
	Sun Jun 28 18:03:48 2026
$end
$version
	Icarus Verilog
$end
$timescale
	1s
$end
$scope module door_lock_tb $end
$var wire 1 ! unlock $end
$var wire 1 " ALARM $end
$var reg 1 # clk $end
$var reg 1 $ enter $end
$var reg 4 % password_entry [3:0] $end
$var reg 1 & reset $end
$scope module dut $end
$var wire 1 # clk $end
$var wire 1 $ enter $end
$var wire 1 ' enter_pulse $end
$var wire 4 ( password_entry [3:0] $end
$var wire 1 & reset $end
$var wire 1 ! unlock $end
$var wire 1 ) correct $end
$var wire 1 " ALARM $end
$var parameter 4 * alarm_time $end
$var parameter 4 + attempts $end
$var parameter 4 , hold $end
$var parameter 4 - password $end
$var parameter 4 . s0 $end
$var parameter 4 / s1 $end
$var parameter 4 0 s2 $end
$var parameter 4 1 s3 $end
$var reg 4 2 alaarm [3:0] $end
$var reg 4 3 count [3:0] $end
$var reg 1 4 enter_d $end
$var reg 4 5 next_state [3:0] $end
$var reg 4 6 state [3:0] $end
$var reg 4 7 timer [3:0] $end
$upscope $end
$upscope $end
$enddefinitions $end
$comment Show the parameter values. $end
$dumpall
b11 1
b10 0
b1 /
b0 .
b1100 -
b1010 ,
b11 +
b1010 *
$end
#0
$dumpvars
bx 7
bx 6
b0 5
x4
bx 3
bx 2
0)
b0 (
0'
1&
b0 %
0$
0#
x"
x!
$end
#5
04
0!
0"
b0 6
b0 3
b0 7
b0 2
1#
#10
b10 5
1'
0#
1$
b101 %
b101 (
#12
0&
#15
0'
b0 5
b10 6
14
1#
#20
0#
0$
#25
04
b0 6
b1 3
1#
#30
b1 5
1'
0#
1$
1)
b1100 %
b1100 (
#35
0'
1!
b1 6
14
1#
#40
0#
#45
b0 3
b1 7
1#
#50
0#
0$
#55
b10 7
04
1#
#60
1'
0#
1$
0)
b1001 %
b1001 (
#65
0'
14
b11 7
1#
#70
0#
0$
#75
b100 7
04
1#
#80
1'
0#
1$
b1000 %
b1000 (
#85
0'
14
b101 7
1#
#90
0#
0$
#95
b110 7
04
1#
#100
0#
#105
b111 7
1#
#110
0#
#115
b1000 7
1#
#120
0#
#125
b1001 7
1#
#130
0#
#135
b0 5
b1010 7
1#
#140
0#
#145
0!
b0 6
b0 7
1#
#150
0#
#155
1#
#160
b10 5
1'
0#
1$
b1101 %
b1101 (
#165
0'
b0 5
14
b10 6
1#
#170
0#
0$
#175
b1 3
b0 6
04
1#
